procal/__init__.py
procal/main.py
procal-0.2.0.dist-info/METADATA
procal-0.2.0.dist-info/WHEEL
procal-0.2.0.dist-info/top_level.txt
procal-0.2.0.dist-info/RECORD
