Metadata-Version: 2.1
Name: procal
Version: 0.2.0
